edgeql_qb/__init__.py
edgeql_qb/expression.py
edgeql_qb/frozendict.py
edgeql_qb/func.py
edgeql_qb/operators.py
edgeql_qb/queries.py
edgeql_qb/render/__init__.py
edgeql_qb/render/condition.py
edgeql_qb/render/delete.py
edgeql_qb/render/expression.py
edgeql_qb/render/func.py
edgeql_qb/render/group.py
edgeql_qb/render/insert.py
edgeql_qb/render/order_by.py
edgeql_qb/render/pagination.py
edgeql_qb/render/query_literal.py
edgeql_qb/render/select.py
edgeql_qb/render/tools.py
edgeql_qb/render/types.py
edgeql_qb/render/update.py
edgeql_qb/render/with_expr.py
edgeql_qb/types.py
elgeql_qb-0.4.1.dist-info/LICENSE
elgeql_qb-0.4.1.dist-info/WHEEL
elgeql_qb-0.4.1.dist-info/METADATA
elgeql_qb-0.4.1.dist-info/RECORD
