Metadata-Version: 2.1
Name: elgeql-qb
Version: 0.4.1
Summary: EdgeQL Query Builder
Home-page: https://github.com/Pentusha/edgeql-qb
License: MIT
Keywords: edgedb,edgeql
Author: Ivan Larin
Author-email: pentusha@gmail.com
Maintainer: Ivan Larin
Maintainer-email: pentusha@gmail.com
Requires-Python: >=3.10,<4.0
Classifier: Development Status :: 2 - Pre-Alpha
Classifier: Intended Audience :: Developers
Classifier: License :: OSI Approved :: MIT License
Classifier: Natural Language :: English
Classifier: Programming Language :: Python :: 3
Classifier: Programming Language :: Python :: 3.10
Classifier: Programming Language :: Python :: 3.11
Project-URL: Repository, https://github.com/Pentusha/edgeql-qb
